README.rst
django_apptest.py
setup.py
django_app_tester.egg-info/PKG-INFO
django_app_tester.egg-info/SOURCES.txt
django_app_tester.egg-info/dependency_links.txt
django_app_tester.egg-info/entry_points.txt
django_app_tester.egg-info/requires.txt
django_app_tester.egg-info/top_level.txt