Metadata-Version: 1.1
Name: django-app-tester
Version: 0.1.1
Summary: A tool that runs the Django test suite for a given application without requiring a fully-configured project
Home-page: https://github.com/shaneallgeier/django-app-tester
Author: Shane Allgeier
Author-email: shaneallgeier@gmail.com
License: UNKNOWN
Keywords: automation,unit tests,django app testing
Platform: UNKNOWN
Classifier: Development Status :: 4 - Beta
Classifier: Environment :: Console
Classifier: Intended Audience :: Developers
Classifier: License :: Public Domain
Classifier: Operating System :: OS Independent
Classifier: Programming Language :: Python
Classifier: Programming Language :: Python :: 2
Classifier: Programming Language :: Unix Shell
